{
  "status": "success",
  "data": {
    "stats": {
      "total": 15688,
      "totalCoins": 15688,
      "totalMarkets": 30022,
      "totalExchanges": 173,
      "totalMarketCap": "1011549548812",
      "total24hVolume": "83668573288"
    },
    "coins": [
      {
        "uuid": "Qwsogvtv82FCd",
        "symbol": "BTC",
        "name": "Bitcoin",
        "color": "#f7931A",
        "iconUrl": "https://cdn.coinranking.com/bOabBYkcX/bitcoin_btc.svg",
        "marketCap": "377846659690",
        "price": "19728.990133582287",
        "listedAt": 1330214400,
        "tier": 1,
        "change": "-1.58",
        "rank": 1,
        "sparkline": [
          "20052.958195757037",
          "20068.415673185908",
          "20115.767004295067",
          "20151.79553492133",
          "20173.98359900712",
          "20144.19551524197",
          "20162.208770468987",
          "20147.737242484403",
          "20138.76685573156",
          "20106.408375512805",
          "20102.17474419897",
          "19830.21686884976",
          "19747.93557178074",
          "19839.30065606472",
          "19824.63075369321",
          "19797.09539502377",
          "19772.233290311957",
          "19808.742569879683",
          "19855.76831812271",
          "19777.004632996584",
          "19704.26427676943",
          "19707.086132953966",
          "19766.88040737313",
          "19750.464844127324",
          "19722.856634721335"
        ],
        "lowVolume": false,
        "coinrankingUrl": "https://coinranking.com/coin/Qwsogvtv82FCd+bitcoin-btc",
        "24hVolume": "46569333780",
        "btcPrice": "1"
      },
      {
        "uuid": "razxDUgYGNAdQ",
        "symbol": "ETH",
        "name": "Ethereum",
        "color": "#3C3C3D",
        "iconUrl": "https://cdn.coinranking.com/rk4RKHOuW/eth.svg",
        "marketCap": "179118874874",
        "price": "1467.936580469876",
        "listedAt": 1438905600,
        "tier": 1,
        "change": "-8.29",
        "rank": 2,
        "sparkline": [
          "1602.505754480464",
          "1603.3597404926763",
          "1602.2756474429334",
          "1616.667064434182",
          "1624.2941844245736",
          "1602.6399720731674",
          "1590.2228896106153",
          "1583.6774096287684",
          "1589.6327478841372",
          "1587.982703647424",
          "1578.6874513205755",
          "1499.049527930076",
          "1491.419248249329",
          "1508.0970531719627",
          "1507.3075816579994",
          "1501.7647573468257",
          "1499.149498354126",
          "1500.9141662921506",
          "1494.7144690361504",
          "1478.3760859132262",
          "1473.4162666661225",
          "1469.118211441754",
          "1477.8054152212123",
          "1469.4067080096927",
          "1464.6445576856984"
        ],
        "lowVolume": false,
        "coinrankingUrl": "https://coinranking.com/coin/razxDUgYGNAdQ+ethereum-eth",
        "24hVolume": "23992179799",
        "btcPrice": "0.07440505421365608"
      },
      {
        "uuid": "HIVsRcGKkPFtW",
        "symbol": "USDT",
        "name": "Tether USD",
        "color": "#22a079",
        "iconUrl": "https://cdn.coinranking.com/mgHqwlCLj/usdt.svg",
        "marketCap": "67881538740",
        "price": "0.9993831331223919",
        "listedAt": 1420761600,
        "tier": 1,
        "change": "-0.26",
        "rank": 3,
        "sparkline": [
          "1.0013732097741592",
          "1.0008065739503496",
          "1.001550841474645",
          "0.998716512304919",
          "1.0015955359113764",
          "1.001030547370717",
          "1.0001923265837873",
          "1.0002947713035182",
          "0.99993558075749",
          "1.0006350755195208",
          "1.0007571196682394",
          "1.0047243880530377",
          "0.9998225391568488",
          "0.9984812667704561",
          "1.0006069254166194",
          "1.0007097780436511",
          "0.9995233437449729",
          "1.0000421236307815",
          "1.0004308244059625",
          "1.001453699604027",
          "1.0002178916073576",
          "1.0002701636810816",
          "0.9995287831493875",
          "1.0007615343359388",
          "1.0000114984554924"
        ],
        "lowVolume": false,
        "coinrankingUrl": "https://coinranking.com/coin/HIVsRcGKkPFtW+tetherusd-usdt",
        "24hVolume": "51377483420",
        "btcPrice": "0.000050655564545154"
      },
      {
        "uuid": "aKzUVe4Hh_CON",
        "symbol": "USDC",
        "name": "USDC",
        "color": "#7894b4",
        "iconUrl": "https://cdn.coinranking.com/jkDf8sQbY/usdc.svg",
        "marketCap": "55828035430",
        "price": "0.9991039052388959",
        "listedAt": 1539043200,
        "tier": 1,
        "change": "-0.33",
        "rank": 4,
        "sparkline": [
          "1.0015561536064541",
          "1.001009500930223",
          "1.0016136879647644",
          "0.9985832221550726",
          "1.001379074923285",
          "1.000968490475061",
          "1.0000762285582985",
          "1.0002686366397426",
          "0.9999191488378584",
          "1.0006455977146655",
          "1.0006648187433005",
          "1.0051056551874755",
          "0.9999520046214432",
          "0.9984911180365781",
          "1.0006062867332342",
          "1.0006782338371132",
          "0.9996291883073025",
          "1.0000501984877737",
          "1.000410680988599",
          "1.0015119938580865",
          "1.0003012951722539",
          "1.0003692994177444",
          "0.9995631352873521",
          "1.000796193690505",
          "1.000049938654595"
        ],
        "lowVolume": false,
        "coinrankingUrl": "https://coinranking.com/coin/aKzUVe4Hh_CON+usdc-usdc",
        "24hVolume": "5765772505",
        "btcPrice": "0.000050641411368453"
      },
      {
        "uuid": "WcwrkfNI4FUAe",
        "symbol": "BNB",
        "name": "Binance Coin",
        "color": "#e8b342",
        "iconUrl": "https://cdn.coinranking.com/B1N19L_dZ/bnb.svg",
        "marketCap": "39523458818",
        "price": "272.809303824991",
        "listedAt": 1503014400,
        "tier": 1,
        "change": "-1.27",
        "rank": 5,
        "sparkline": [
          "275.85649674729075",
          "274.8748093824045",
          "274.2282391998841",
          "276.11878693559356",
          "276.1402184828276",
          "275.48352275510626",
          "276.073935221105",
          "274.9701893265758",
          "275.72563010901507",
          "276.298956021646",
          "275.89639305965056",
          "271.3447008827383",
          "269.9012578195911",
          "271.2801482734691",
          "271.6860509828262",
          "271.0832687221572",
          "271.3554119638009",
          "271.9645638379569",
          "271.90061105195025",
          "270.7044232408568",
          "270.3973678556966",
          "271.55114434484994",
          "273.14354667439306",
          "272.74405832564224",
          "272.24920188307584"
        ],
        "lowVolume": false,
        "coinrankingUrl": "https://coinranking.com/coin/WcwrkfNI4FUAe+binancecoin-bnb",
        "24hVolume": "1091731605",
        "btcPrice": "0.013827839234438082"
      },
      {
        "uuid": "vSo2fu9iE1s0Y",
        "symbol": "BUSD",
        "name": "Binance USD",
        "color": "#f0b90b",
        "iconUrl": "https://cdn.coinranking.com/6SJHRfClq/busd.svg",
        "marketCap": "20657529028",
        "price": "0.9996941009251864",
        "listedAt": 1563197940,
        "tier": 1,
        "change": "-0.15",
        "rank": 6,
        "sparkline": [
          "1.000851326628433",
          "1.000198117014592",
          "1.0011481186566724",
          "0.9984756850653186",
          "1.0014051545406821",
          "1.0009221075465657",
          "1.0001609137573921",
          "1.000362017549364",
          "0.9999672750582287",
          "1.0006858808390344",
          "1.0009872293947124",
          "1.0048288420376452",
          "0.9998761015865384",
          "0.998591362933266",
          "1.0007129254159526",
          "1.0008804111322485",
          "0.9995537046217824",
          "1.0002189229313556",
          "1.0005806390619834",
          "1.0015644542398232",
          "1.0003345364704963",
          "1.0004327484639015",
          "0.9996637982317566",
          "1.0008580121458501",
          "1.00005232372021"
        ],
        "lowVolume": false,
        "coinrankingUrl": "https://coinranking.com/coin/vSo2fu9iE1s0Y+binanceusd-busd",
        "24hVolume": "8775988710",
        "btcPrice": "0.000050671326517799"
      },
      {
        "uuid": "qzawljRxB5bYu",
        "symbol": "ADA",
        "name": "Cardano",
        "color": "#3cc8c8",
        "iconUrl": "https://cdn.coinranking.com/ryY28nXhW/ada.svg",
        "marketCap": "14541556869",
        "price": "0.46738654877141944",
        "listedAt": 1506902400,
        "tier": 1,
        "change": "-0.81",
        "rank": 7,
        "sparkline": [
          "0.4696536374432701",
          "0.46969506701513114",
          "0.4705037206997151",
          "0.47569311395109887",
          "0.4760482054714534",
          "0.47494943233092546",
          "0.47562671868397227",
          "0.4731655494851062",
          "0.47482492988612945",
          "0.4755666858306177",
          "0.4760553344892249",
          "0.46899172821068996",
          "0.46794254887298353",
          "0.4692378386996725",
          "0.46932192156513153",
          "0.468269578797271",
          "0.4681582717072536",
          "0.46920705485427117",
          "0.4682864104906914",
          "0.46577867596125905",
          "0.46493970683041763",
          "0.46566653879568776",
          "0.4681219645576345",
          "0.4660764352295209",
          "0.4661781801985336"
        ],
        "lowVolume": false,
        "coinrankingUrl": "https://coinranking.com/coin/qzawljRxB5bYu+cardano-ada",
        "24hVolume": "967172495",
        "btcPrice": "0.000023690343276914"
      },
      {
        "uuid": "-l8Mn2pVlRs-p",
        "symbol": "XRP",
        "name": "XRP",
        "color": "#000000",
        "iconUrl": "https://cdn.coinranking.com/B1oPuTyfX/xrp.svg",
        "marketCap": "14350048672",
        "price": "0.3255959649929459",
        "listedAt": 1421798400,
        "tier": 1,
        "change": "-3.04",
        "rank": 8,
        "sparkline": [
          "0.33596323639180564",
          "0.33821869210724215",
          "0.33702770236931573",
          "0.33977646695274355",
          "0.3406606030286377",
          "0.33951188103664937",
          "0.3377061247151668",
          "0.33592315161949",
          "0.3348668304002235",
          "0.3336138944460249",
          "0.3320529405755168",
          "0.32790175144873007",
          "0.32596421039173035",
          "0.32604468778670187",
          "0.32787483724858474",
          "0.32801501608405115",
          "0.32902839552484847",
          "0.3295992625600386",
          "0.32881418010471836",
          "0.32722569114004957",
          "0.3260056832563869",
          "0.32594508032641345",
          "0.32638010704682663",
          "0.3242638246765087",
          "0.3247386198170247"
        ],
        "lowVolume": false,
        "coinrankingUrl": "https://coinranking.com/coin/-l8Mn2pVlRs-p+xrp-xrp",
        "24hVolume": "2064493889",
        "btcPrice": "0.000016503427838342"
      },
      {
        "uuid": "zNZHO_Sjf",
        "symbol": "SOL",
        "name": "Solana",
        "color": "#9cddec",
        "iconUrl": "https://cdn.coinranking.com/yvUG4Qex5/solana.svg",
        "marketCap": "11590606915",
        "price": "32.74371773500635",
        "listedAt": 1586539320,
        "tier": 1,
        "change": "-1.01",
        "rank": 9,
        "sparkline": [
          "33.094853473307566",
          "33.16502283176241",
          "33.228791232435256",
          "34.10924840312076",
          "34.54178637990024",
          "33.963997109544664",
          "33.88996554126175",
          "33.848019770013025",
          "33.864491374146574",
          "33.74031632032386",
          "33.71914074846792",
          "33.1638907792283",
          "33.00678023090994",
          "33.25805433073353",
          "33.418739149290595",
          "33.44850699590763",
          "33.44178637163708",
          "33.58892989890181",
          "33.43971369240996",
          "33.16500014535467",
          "33.06572212896263",
          "32.9975262696292",
          "33.07953801512507",
          "32.894086587047774",
          "32.678700891047725"
        ],
        "lowVolume": false,
        "coinrankingUrl": "https://coinranking.com/coin/zNZHO_Sjf+solana-sol",
        "24hVolume": "1227486790",
        "btcPrice": "0.001659675305897723"
      },
      {
        "uuid": "9K7m6ufraZ6gh",
        "symbol": "HEX",
        "name": "HEX",
        "color": "#ffcd00",
        "iconUrl": "https://cdn.coinranking.com/iseN4Am58/hex-vector.svg",
        "marketCap": "8879776802",
        "price": "0.034363307906345814",
        "listedAt": 1589361480,
        "tier": 1,
        "change": "-6.80",
        "rank": 10,
        "sparkline": [
          "0.036866829041286485",
          "0.03656399651665005",
          "0.03668878379252147",
          "0.036485013110784704",
          "0.03641514925315951",
          "0.03617377578971723",
          "0.03618042933779944",
          "0.03640375504145784",
          "0.03587673145987225",
          "0.03556435436280447",
          "0.03513908879569264",
          "0.034747997900967977",
          "0.03409766695623804",
          "0.03443623233949011",
          "0.03467529542482515",
          "0.03442205249945902",
          "0.03436424111510026",
          "0.034507301925197006",
          "0.03457297447382319",
          "0.03446382547009335",
          "0.03451167648499259",
          "0.034516795518477354",
          "0.03449154744615737",
          "0.03444733974656472",
          "0.03431580737679938"
        ],
        "lowVolume": false,
        "coinrankingUrl": "https://coinranking.com/coin/9K7m6ufraZ6gh+hex-hex",
        "24hVolume": "2732108",
        "btcPrice": "0.000001741767200129"
      },
      {
        "uuid": "a91GCGd_u96cF",
        "symbol": "DOGE",
        "name": "Dogecoin",
        "color": "#c2a633",
        "iconUrl": "https://cdn.coinranking.com/H1arXIuOZ/doge.svg",
        "marketCap": "7869509319",
        "price": "0.05931607735907905",
        "listedAt": 1391212800,
        "tier": 1,
        "change": "-1.60",
        "rank": 11,
        "sparkline": [
          "0.060334864237837314",
          "0.06038677994464795",
          "0.06029063738049072",
          "0.060707253520313226",
          "0.060705918949259655",
          "0.06059807036135623",
          "0.0605768231918217",
          "0.060391902758295944",
          "0.06056249495740999",
          "0.060573546673699324",
          "0.0604988668344641",
          "0.059594558402935704",
          "0.058908326089188244",
          "0.05923858434486621",
          "0.059384738861085556",
          "0.0593557404394452",
          "0.05939194982056917",
          "0.05957363710059582",
          "0.05959716153074795",
          "0.05919558942164131",
          "0.058875541810497575",
          "0.058573611952768355",
          "0.05891967509668368",
          "0.05898070227433115",
          "0.059131579175838174"
        ],
        "lowVolume": false,
        "coinrankingUrl": "https://coinranking.com/coin/a91GCGd_u96cF+dogecoin-doge",
        "24hVolume": "438139676",
        "btcPrice": "0.000003006544022652"
      },
      {
        "uuid": "25W7FG7om",
        "symbol": "DOT",
        "name": "Polkadot",
        "color": "#d64cA8",
        "iconUrl": "https://cdn.coinranking.com/RsljYqnbu/polkadot.svg",
        "marketCap": "7552378083",
        "price": "6.890986858976515",
        "listedAt": 1598365200,
        "tier": 1,
        "change": "-2.18",
        "rank": 12,
        "sparkline": [
          "7.040952507398714",
          "7.0504868544914014",
          "7.0414673184215335",
          "7.123049604803824",
          "7.142984398461093",
          "7.103608451610552",
          "7.107184058408936",
          "7.072226301928314",
          "7.099814161747748",
          "7.102446980398351",
          "7.102532314814599",
          "6.991649883701321",
          "6.946330967353932",
          "6.996780246394552",
          "6.999786198684404",
          "6.973644984526015",
          "6.967312022726068",
          "6.973103014480994",
          "6.9701526149357145",
          "6.930959089132061",
          "6.919411767355984",
          "6.922762789482181",
          "6.9466728273429705",
          "6.910458405460389",
          "6.890215380228114"
        ],
        "lowVolume": false,
        "coinrankingUrl": "https://coinranking.com/coin/25W7FG7om+polkadot-dot",
        "24hVolume": "634131198",
        "btcPrice": "0.000349282290290511"
      },
      {
        "uuid": "VLqpJwogdhHNb",
        "symbol": "LINK",
        "name": "Chainlink",
        "color": "#4680b0",
        "iconUrl": "https://cdn.coinranking.com/9NOP9tOem/chainlink.svg",
        "marketCap": "7511258931",
        "price": "7.511938943917993",
        "listedAt": 1505952000,
        "tier": 1,
        "change": "4.36",
        "rank": 13,
        "sparkline": [
          "7.189752154633632",
          "7.203456364906252",
          "7.249078028762345",
          "7.370395067500761",
          "7.369041451705849",
          "7.332753983634924",
          "7.319969030666603",
          "7.268073270820404",
          "7.313181569220831",
          "7.303851884360499",
          "7.291332970611814",
          "7.135230509581951",
          "7.151899478224997",
          "7.2599284883109405",
          "7.3031847260310565",
          "7.3299872296879",
          "7.319578569428676",
          "7.368214333045824",
          "7.458424899962336",
          "7.494101721122028",
          "7.508735705900256",
          "7.559760421059834",
          "7.577597244292939",
          "7.502400166478006",
          "7.488588184631994"
        ],
        "lowVolume": false,
        "coinrankingUrl": "https://coinranking.com/coin/VLqpJwogdhHNb+chainlink-link",
        "24hVolume": "636735843",
        "btcPrice": "0.000380756384034646"
      },
      {
        "uuid": "uW2tk-ILY0ii",
        "symbol": "MATIC",
        "name": "Polygon",
        "color": "#8247e5",
        "iconUrl": "https://cdn.coinranking.com/WulYRq14o/polygon.png",
        "marketCap": "7149416756",
        "price": "0.8188355108675791",
        "listedAt": 1558961160,
        "tier": 1,
        "change": "-2.98",
        "rank": 14,
        "sparkline": [
          "0.8413097103873566",
          "0.8419727282735072",
          "0.8439254502986481",
          "0.8605328524070908",
          "0.8653139698602303",
          "0.8606924411551551",
          "0.8622335370469706",
          "0.8549037676657212",
          "0.8591599435370795",
          "0.8573884706515945",
          "0.8550213863289493",
          "0.8340881422736517",
          "0.825495681598585",
          "0.8318094400799375",
          "0.8343458190261971",
          "0.8362551415175893",
          "0.8356932672722617",
          "0.8406776935129439",
          "0.8380392375433801",
          "0.8338712378681578",
          "0.82585950618429",
          "0.8232646932116272",
          "0.8270091076953435",
          "0.8221137205168464",
          "0.8175825131701652"
        ],
        "lowVolume": false,
        "coinrankingUrl": "https://coinranking.com/coin/uW2tk-ILY0ii+polygon-matic",
        "24hVolume": "485021994",
        "btcPrice": "0.000041504177625076"
      },
      {
        "uuid": "xz24e0BjL",
        "symbol": "SHIB",
        "name": "SHIBA INU",
        "color": "#fda32b",
        "iconUrl": "https://cdn.coinranking.com/D69LfI-tm/shib.png",
        "marketCap": "6879121702",
        "price": "0.000011668386062405",
        "listedAt": 1620650373,
        "tier": 1,
        "change": "-2.04",
        "rank": 15,
        "sparkline": [
          "0.000011892442660317",
          "0.000011897104198316",
          "0.000011948350521698",
          "0.00001207139968237",
          "0.000012078624495717",
          "0.000012040556623994",
          "0.000012038290487612",
          "0.000012002971430263",
          "0.000012068490959767",
          "0.00001203998403363",
          "0.000012019076660097",
          "0.000011834025085351",
          "0.000011714194908424",
          "0.000011787767334658",
          "0.000011804324263838",
          "0.000011822558813597",
          "0.000011811530298883",
          "0.000011850608729467",
          "0.000011826305788215",
          "0.000011753163959852",
          "0.000011719566151891",
          "0.000011666589552497",
          "0.000011691272799528",
          "0.000011649381810685",
          "0.000011639273166595"
        ],
        "lowVolume": false,
        "coinrankingUrl": "https://coinranking.com/coin/xz24e0BjL+shibainu-shib",
        "24hVolume": "444391456",
        "btcPrice": "5.91433519e-10"
      },
      {
        "uuid": "MoTuySvg7",
        "symbol": "DAI",
        "name": "Dai",
        "color": null,
        "iconUrl": "https://cdn.coinranking.com/mAZ_7LwOE/mutli-collateral-dai.svg",
        "marketCap": "6360872630",
        "price": "0.9987750293644148",
        "listedAt": 1585574040,
        "tier": 1,
        "change": "-0.28",
        "rank": 16,
        "sparkline": [
          "1.001078308595275",
          "1.0006211221212742",
          "1.0009681033304798",
          "0.9989572832531405",
          "1.00067319094788",
          "1.0008377334071272",
          "1.0000351493734811",
          "1.000095905070409",
          "0.9996904175483534",
          "1.0004194489021023",
          "1.0003013065805086",
          "1.0048493280401845",
          "0.9996740589357832",
          "0.9982365766583756",
          "1.000232094673472",
          "1.0002795621282183",
          "0.9992482043943424",
          "0.9996704791172653",
          "0.9997997580614443",
          "1.0009635283439802",
          "1.0000066852526397",
          "1.0001981033253526",
          "0.9993982460990052",
          "1.0005609809652165",
          "0.9998223800852415"
        ],
        "lowVolume": false,
        "coinrankingUrl": "https://coinranking.com/coin/MoTuySvg7+dai-dai",
        "24hVolume": "195357795",
        "btcPrice": "0.000050624741692395"
      },
      {
        "uuid": "VINVMYf0u",
        "symbol": "STETH",
        "name": "Lido Staked Ether",
        "color": "#41c0f5",
        "iconUrl": "https://cdn.coinranking.com/UJ-dQdgYY/8085.png",
        "marketCap": "6257111051",
        "price": "1451.4015249362214",
        "listedAt": 1627012680,
        "tier": 1,
        "change": "-6.65",
        "rank": 17,
        "sparkline": [
          "1559.258921708083",
          "1561.8982972290585",
          "1565.5245694891146",
          "1582.6367954442042",
          "1598.7653912126168",
          "1577.4905846562913",
          "1565.539925445601",
          "1558.8002637756808",
          "1566.9384346507911",
          "1566.2006400042658",
          "1558.2710930834446",
          "1481.3141693804778",
          "1471.983330823812",
          "1488.3424006149326",
          "1489.5830323549228",
          "1484.0376413190686",
          "1479.7317628251355",
          "1482.6651327840564",
          "1476.80908703204",
          "1461.6736112095014",
          "1455.870015068616",
          "1451.7848758935622",
          "1460.8453455940216",
          "1453.2063364299102",
          "1447.2100794984146"
        ],
        "lowVolume": false,
        "coinrankingUrl": "https://coinranking.com/coin/VINVMYf0u+lidostakedether-steth",
        "24hVolume": "19748583",
        "btcPrice": "0.07356694463877678"
      },
      {
        "uuid": "qUhEFk1I61atv",
        "symbol": "TRX",
        "name": "TRON",
        "color": "#eb0029",
        "iconUrl": "https://cdn.coinranking.com/behejNqQs/trx.svg",
        "marketCap": "6252742517",
        "price": "0.06139821288733505",
        "listedAt": 1505260800,
        "tier": 1,
        "change": "0.90",
        "rank": 18,
        "sparkline": [
          "0.06076728304556454",
          "0.060943631305943546",
          "0.06108749998000358",
          "0.06153593774468038",
          "0.06180754951832331",
          "0.061679291637454864",
          "0.06160645610595333",
          "0.06155810874963264",
          "0.061586412583927864",
          "0.06160578734265506",
          "0.061648046254709855",
          "0.06127691046204935",
          "0.06114220042818095",
          "0.06131007143621706",
          "0.061360976209079696",
          "0.06132460157810043",
          "0.061325356097774904",
          "0.06142098017722084",
          "0.06146634915963141",
          "0.06141205757145969",
          "0.06114208721699937",
          "0.06127860333938455",
          "0.06144819838778063",
          "0.06135288910247237",
          "0.061306893990334246"
        ],
        "lowVolume": false,
        "coinrankingUrl": "https://coinranking.com/coin/qUhEFk1I61atv+tron-trx",
        "24hVolume": "738266931",
        "btcPrice": "0.000003112080875484"
      },
      {
        "uuid": "N2IgQ9Xme",
        "symbol": "BIT",
        "name": "BitDAO ",
        "color": "#000000",
        "iconUrl": "https://cdn.coinranking.com/0ClFW1IpO/bitdao.png",
        "marketCap": "4952924004",
        "price": "0.49529240037121974",
        "listedAt": 1639033619,
        "tier": 1,
        "change": "-12.46",
        "rank": 19,
        "sparkline": [
          "0.565955506287145",
          "0.5673633277905552",
          "0.5680862157221529",
          "0.5599721766974255",
          "0.5568221530811378",
          "0.5400100512178012",
          "0.5339099290853901",
          "0.5304759094353687",
          "0.532973214150489",
          "0.5325781486711236",
          "0.5298507207347236",
          "0.5246618874992232",
          "0.5259151115452025",
          "0.5316052083201049",
          "0.5342828878873114",
          "0.5339753192236902",
          "0.5294081085751832",
          "0.5279662539866313",
          "0.5248107163110703",
          "0.5198230209835206",
          "0.5146489187162232",
          "0.505161148347912",
          "0.5021485615862772",
          "0.49850367314689553",
          "0.4960272292608658"
        ],
        "lowVolume": false,
        "coinrankingUrl": "https://coinranking.com/coin/N2IgQ9Xme+bitdao-bit",
        "24hVolume": "5972790",
        "btcPrice": "0.000025104802476846"
      },
      {
        "uuid": "x4WXHge-vvFY",
        "symbol": "WBTC",
        "name": "Wrapped BTC",
        "color": "#000000",
        "iconUrl": "https://cdn.coinranking.com/o3-8cvCHu/wbtc[1].svg",
        "marketCap": "4917354051",
        "price": "19727.982450871343",
        "listedAt": 1549894980,
        "tier": 1,
        "change": "-1.55",
        "rank": 20,
        "sparkline": [
          "20038.63597117263",
          "20052.184175978662",
          "20094.459628035027",
          "20135.768310741343",
          "20180.901577771314",
          "20138.388290055",
          "20156.178563191865",
          "20136.8520277212",
          "20133.85417344329",
          "20112.088021382297",
          "20098.424244704318",
          "19852.959418439623",
          "19747.906572855944",
          "19829.584358434073",
          "19827.894655642573",
          "19799.2143111661",
          "19768.62782166212",
          "19804.519913559863",
          "19851.85463088556",
          "19787.673784352137",
          "19703.905406813803",
          "19703.805759182873",
          "19757.658644683466",
          "19749.197782128624",
          "19723.5764545578"
        ],
        "lowVolume": false,
        "coinrankingUrl": "https://coinranking.com/coin/x4WXHge-vvFY+wrappedbtc-wbtc",
        "24hVolume": "86815087",
        "btcPrice": "0.9999489237561516"
      },
      {
        "uuid": "mqtUpyBxu8O8",
        "symbol": "LEO",
        "name": "LEO",
        "color": "#063f35",
        "iconUrl": "https://cdn.coinranking.com/12EKqY08r/leo.svg",
        "marketCap": "4789392149",
        "price": "4.857557066516311",
        "listedAt": 1561471620,
        "tier": 1,
        "change": "-6.06",
        "rank": 21,
        "sparkline": [
          "5.1462679717109525",
          "5.124659656020934",
          "5.120991133406382",
          "5.119276933274149",
          "5.12547682159357",
          "5.119574189445589",
          "5.119492232792906",
          "5.122315948445467",
          "5.118736168307128",
          "5.119147223493425",
          "5.126926600321062",
          "5.083682477548698",
          "5.099147861928414",
          "5.092080905694586",
          "5.032414253078262",
          "4.956989546942117",
          "4.954708254468784",
          "4.953923335782931",
          "4.959957982085033",
          "4.954102067375352",
          "4.903360384553245",
          "4.87255884446184",
          "4.874645530046348",
          "4.872656008941425",
          "4.860103617757554"
        ],
        "lowVolume": false,
        "coinrankingUrl": "https://coinranking.com/coin/mqtUpyBxu8O8+leo-leo",
        "24hVolume": "2485745",
        "btcPrice": "0.000246214176885206"
      },
      {
        "uuid": "_H5FVG9iW",
        "symbol": "UNI",
        "name": "Uniswap",
        "color": "#ff007a",
        "iconUrl": "https://cdn.coinranking.com/1heSvUgtl/uniswap-v2.svg?size=48x48",
        "marketCap": "4533639010",
        "price": "5.875415961244163",
        "listedAt": 1600323371,
        "tier": 1,
        "change": "-2.13",
        "rank": 22,
        "sparkline": [
          "5.980772767402791",
          "5.97165127676782",
          "5.975732751092091",
          "6.1107475040098596",
          "6.122391402381545",
          "6.079184609265282",
          "6.135623060544712",
          "6.098158834055915",
          "6.103823094522214",
          "6.093915017382491",
          "6.074070254669561",
          "5.892895200379038",
          "5.926520558103972",
          "5.963594935920134",
          "5.95300467192735",
          "5.946001672787255",
          "5.938380184043084",
          "5.950715915522488",
          "5.955526634061703",
          "5.909547569749743",
          "5.882728264308084",
          "5.874861329540876",
          "5.907310558519695",
          "5.873932441396025",
          "5.8611998264060885"
        ],
        "lowVolume": false,
        "coinrankingUrl": "https://coinranking.com/coin/_H5FVG9iW+uniswap-uni",
        "24hVolume": "148056529",
        "btcPrice": "0.000297806219247033"
      },
      {
        "uuid": "Knsels4_Ol-Ny",
        "symbol": "ATOM",
        "name": "Cosmos",
        "color": "#5064fb",
        "iconUrl": "https://cdn.coinranking.com/HJzHboruM/atom.svg",
        "marketCap": "4415146913",
        "price": "15.090074170263232",
        "listedAt": 1552520100,
        "tier": 1,
        "change": "12.18",
        "rank": 23,
        "sparkline": [
          "13.42707839758992",
          "13.464663318765151",
          "13.499428633755631",
          "13.996096683960648",
          "14.499624425386475",
          "14.316349023967847",
          "14.469668994979898",
          "14.44039227800872",
          "14.643667137774296",
          "14.610657974532966",
          "14.673813840923016",
          "14.75554357221504",
          "14.787204540239062",
          "14.925099104125708",
          "14.993149283592825",
          "15.238112670711162",
          "15.180099635129668",
          "15.26328084872276",
          "15.365136257806759",
          "15.34585431013856",
          "14.958963339929404",
          "15.078107412110924",
          "15.199030082028273",
          "15.088065723117023",
          "15.048625016432412"
        ],
        "lowVolume": false,
        "coinrankingUrl": "https://coinranking.com/coin/Knsels4_Ol-Ny+cosmos-atom",
        "24hVolume": "901467226",
        "btcPrice": "0.000764868047887419"
      },
      {
        "uuid": "dvUj0CzDZ",
        "symbol": "AVAX",
        "name": "Avalanche",
        "color": "#e84242",
        "iconUrl": "https://cdn.coinranking.com/S0C6Cw2-w/avax-avalanche.png",
        "marketCap": "3980306193",
        "price": "18.097743468742767",
        "listedAt": 1600961596,
        "tier": 1,
        "change": "-3.40",
        "rank": 24,
        "sparkline": [
          "18.63885246261384",
          "18.705234986630355",
          "18.74456109233194",
          "19.07539037921835",
          "19.10498886429514",
          "18.991092699968778",
          "18.951260296302593",
          "18.852712167299778",
          "18.981958109697384",
          "18.96195364439782",
          "18.947522440053962",
          "18.51777008362764",
          "18.41802772207586",
          "18.55055319167055",
          "18.54983527593293",
          "18.550818837798847",
          "18.421480048661344",
          "18.488971527134463",
          "18.467359002605097",
          "18.297857534844898",
          "18.205109651267033",
          "18.159891625730474",
          "18.205611614581333",
          "18.094350817241924",
          "18.062362225552302"
        ],
        "lowVolume": false,
        "coinrankingUrl": "https://coinranking.com/coin/dvUj0CzDZ+avalanche-avax",
        "24hVolume": "515625319",
        "btcPrice": "0.000917317275045779"
      },
      {
        "uuid": "D7B1x_ks7WhV5",
        "symbol": "LTC",
        "name": "Litecoin",
        "color": "#345d9d",
        "iconUrl": "https://cdn.coinranking.com/BUvPxmc9o/ltcnew.svg",
        "marketCap": "3957443531",
        "price": "55.84458220578425",
        "listedAt": 1382572800,
        "tier": 1,
        "change": "-5.77",
        "rank": 25,
        "sparkline": [
          "59.117715754701656",
          "59.216963060040605",
          "59.356210768027594",
          "59.9181214268393",
          "60.139586314439136",
          "60.071289349639216",
          "60.171994133351944",
          "59.687028604219606",
          "59.6656545448827",
          "59.714029001198",
          "59.79935720444369",
          "58.43617449957562",
          "57.22694478382886",
          "57.13124631819086",
          "57.18505620504711",
          "56.908563966321985",
          "56.73926655760526",
          "56.908010340112035",
          "56.901205574977354",
          "56.50304837337723",
          "56.21317126863512",
          "56.39361782943636",
          "56.50977955767575",
          "56.08738927162521",
          "55.80171474306524"
        ],
        "lowVolume": false,
        "coinrankingUrl": "https://coinranking.com/coin/D7B1x_ks7WhV5+litecoin-ltc",
        "24hVolume": "797273019",
        "btcPrice": "0.002830584932511408"
      },
      {
        "uuid": "hnfQfsYfeIGUQ",
        "symbol": "ETC",
        "name": "Ethereum Classic",
        "color": "#699070",
        "iconUrl": "https://cdn.coinranking.com/rJfyor__W/etc.svg",
        "marketCap": "3937726400",
        "price": "33.854481246705824",
        "listedAt": 1469577600,
        "tier": 1,
        "change": "-5.39",
        "rank": 26,
        "sparkline": [
          "35.870703760557674",
          "36.22452645085807",
          "36.22032621595979",
          "37.960355126603304",
          "38.43631866322463",
          "37.33416777784857",
          "37.515844227179656",
          "37.764341666174",
          "38.47798392955802",
          "38.30356915395011",
          "38.30630914643536",
          "37.15266105034771",
          "37.40820628467765",
          "37.42383249251611",
          "37.61348279248804",
          "37.60925695135002",
          "37.496429034635405",
          "37.26120970644612",
          "37.204735165269874",
          "36.62634052770732",
          "35.71094091172265",
          "35.4652799970958",
          "35.0560264293927",
          "33.95758378811145",
          "33.64016013911256"
        ],
        "lowVolume": false,
        "coinrankingUrl": "https://coinranking.com/coin/hnfQfsYfeIGUQ+ethereumclassic-etc",
        "24hVolume": "3555505041",
        "btcPrice": "0.001715976388932316"
      },
      {
        "uuid": "PDKcptVnzJTmN",
        "symbol": "OKB",
        "name": "OKB",
        "color": "#2d60e0",
        "iconUrl": "https://cdn.coinranking.com/xcZdYtX6E/okx.png",
        "marketCap": "3867428482",
        "price": "15.17665923232171",
        "listedAt": 1538524800,
        "tier": 1,
        "change": "-2.11",
        "rank": 27,
        "sparkline": [
          "15.433981426856137",
          "15.33097545832339",
          "15.288331879914224",
          "15.347786466837272",
          "15.416992939358698",
          "15.360726849328312",
          "15.352740507765162",
          "15.354336378762001",
          "15.408111077993018",
          "15.41086602053271",
          "15.439005874385302",
          "15.274858326627093",
          "15.281540149130656",
          "15.33264267287909",
          "15.22261012237277",
          "15.181980743742658",
          "15.194564520427082",
          "15.24524269874036",
          "15.233841596610404",
          "15.208347071543526",
          "15.187808578547141",
          "15.171037363799122",
          "15.17525503625876",
          "15.146094277622375",
          "15.180269986225236"
        ],
        "lowVolume": false,
        "coinrankingUrl": "https://coinranking.com/coin/PDKcptVnzJTmN+okb-okb",
        "24hVolume": "21420187",
        "btcPrice": "0.000769256770344687"
      },
      {
        "uuid": "NfeOYfNcl",
        "symbol": "FTT",
        "name": "FTX Token",
        "color": "#77d9ed",
        "iconUrl": "https://cdn.coinranking.com/WyBm4_EzM/ftx-exchange.svg",
        "marketCap": "3233244524",
        "price": "24.13314742569663",
        "listedAt": 1566222960,
        "tier": 1,
        "change": "-3.24",
        "rank": 28,
        "sparkline": [
          "24.824557592170255",
          "24.694006640406194",
          "24.655611444122822",
          "24.86961195607198",
          "24.89402559066896",
          "24.77229814624148",
          "24.764749882965095",
          "24.699109471706727",
          "24.76495071503993",
          "24.811541655650554",
          "24.776186327757546",
          "24.290202780787038",
          "24.227407555018132",
          "24.37878601352429",
          "24.345148246429464",
          "24.259797031281135",
          "24.255985875151982",
          "24.29703614654059",
          "24.306948303751113",
          "24.150189613748125",
          "24.07814818300052",
          "24.103275926829394",
          "24.211549481854597",
          "24.15105132239552",
          "24.110574679237416"
        ],
        "lowVolume": false,
        "coinrankingUrl": "https://coinranking.com/coin/NfeOYfNcl+ftxtoken-ftt",
        "24hVolume": "89279571",
        "btcPrice": "0.001223232778885001"
      },
      {
        "uuid": "3mVx2FX_iJFp5",
        "symbol": "XMR",
        "name": "Monero",
        "color": "#ff7519",
        "iconUrl": "https://cdn.coinranking.com/Syz-oSd_Z/xmr.svg",
        "marketCap": "2648146425",
        "price": "145.70371902632525",
        "listedAt": 1422489600,
        "tier": 1,
        "change": "-2.08",
        "rank": 29,
        "sparkline": [
          "148.15185165321333",
          "148.28508910116224",
          "148.45982967328027",
          "150.09358024904955",
          "150.58716950256226",
          "149.92561141987906",
          "149.30704212974186",
          "148.69085231287488",
          "148.72691107757507",
          "148.6469401170109",
          "148.7931094732903",
          "146.57670175142795",
          "144.960448077288",
          "145.64951413467162",
          "145.88155287732016",
          "145.32828056291123",
          "144.51931740571794",
          "144.91839239027684",
          "145.53637069939666",
          "145.19886813239378",
          "145.00669576395873",
          "145.41174723198642",
          "146.07876216771115",
          "145.26410162779248",
          "145.13272865784603"
        ],
        "lowVolume": false,
        "coinrankingUrl": "https://coinranking.com/coin/3mVx2FX_iJFp5+monero-xmr",
        "24hVolume": "170500751",
        "btcPrice": "0.007385259865800801"
      },
      {
        "uuid": "DCrsaMv68",
        "symbol": "NEAR",
        "name": "NEAR Protocol",
        "color": "#000000",
        "iconUrl": "https://cdn.coinranking.com/Cth83dCnl/near.png",
        "marketCap": "2548028685",
        "price": "4.1919099199599605",
        "listedAt": 1615164591,
        "tier": 1,
        "change": "-4.34",
        "rank": 30,
        "sparkline": [
          "4.366270464377691",
          "4.368345106681528",
          "4.353238595291261",
          "4.397743023588128",
          "4.402370388860217",
          "4.364451756303375",
          "4.375970296495254",
          "4.350876905206687",
          "4.362264866936905",
          "4.356058801921935",
          "4.340184627603061",
          "4.264550912689858",
          "4.243921404994421",
          "4.250212997547907",
          "4.2470465321503355",
          "4.243877104550447",
          "4.236948605411565",
          "4.251795495280912",
          "4.243801485131817",
          "4.184653598165147",
          "4.16955135690699",
          "4.163610870361664",
          "4.1747831913310165",
          "4.175610562346085",
          "4.177163692670388"
        ],
        "lowVolume": false,
        "coinrankingUrl": "https://coinranking.com/coin/DCrsaMv68+nearprotocol-near",
        "24hVolume": "374775126",
        "btcPrice": "0.000212474632080867"
      },
      {
        "uuid": "ZlZpzOJo43mIo",
        "symbol": "BCH",
        "name": "Bitcoin Cash",
        "color": "#8dc451",
        "iconUrl": "https://cdn.coinranking.com/By8ziihX7/bch.svg",
        "marketCap": "2258126019",
        "price": "118.03245089843628",
        "listedAt": 1541808000,
        "tier": 1,
        "change": "0.56",
        "rank": 31,
        "sparkline": [
          "117.50984583298371",
          "117.66262210182312",
          "117.96079440615745",
          "119.46210935561491",
          "119.84495803794515",
          "119.68487496103485",
          "119.8240400252507",
          "119.43942021014841",
          "120.10419873132727",
          "120.37825508269654",
          "121.19476850366027",
          "118.50696464604563",
          "118.39195723214833",
          "118.68899270740991",
          "118.78434741389734",
          "118.64014203366852",
          "118.59519087707582",
          "119.5538547353013",
          "119.87835943664214",
          "118.78915416114043",
          "117.80285566886137",
          "117.8954739175394",
          "118.2494596255753",
          "117.60586732124663",
          "117.80721159059546"
        ],
        "lowVolume": false,
        "coinrankingUrl": "https://coinranking.com/coin/ZlZpzOJo43mIo+bitcoincash-bch",
        "24hVolume": "265046414",
        "btcPrice": "0.005982690958799955"
      },
      {
        "uuid": "65PHZTpmE55b",
        "symbol": "CRO",
        "name": "Cronos",
        "color": "#01275d",
        "iconUrl": "https://cdn.coinranking.com/2o91jm73M/cro.svg",
        "marketCap": "2117639962",
        "price": "0.10576248853028418",
        "listedAt": 1548953220,
        "tier": 1,
        "change": "-2.99",
        "rank": 32,
        "sparkline": [
          "0.10998228048543973",
          "0.10964177546009786",
          "0.10961155835386584",
          "0.11076322284464918",
          "0.11070401309400575",
          "0.10980969987947622",
          "0.10948716254528391",
          "0.10936515334391182",
          "0.10947872628781402",
          "0.10947880007665098",
          "0.10955407071275894",
          "0.10678086786209723",
          "0.10628478694054146",
          "0.10738284205160785",
          "0.10744752636812652",
          "0.1072741511297442",
          "0.10657456992920772",
          "0.10683399052908288",
          "0.10708983731730468",
          "0.1065817168830156",
          "0.10597529217018631",
          "0.10587937572676306",
          "0.10624277511942322",
          "0.10596067103501106",
          "0.1057143514558785"
        ],
        "lowVolume": false,
        "coinrankingUrl": "https://coinranking.com/coin/65PHZTpmE55b+cronos-cro",
        "24hVolume": "35710562",
        "btcPrice": "0.000005360765442842"
      },
      {
        "uuid": "f3iaFeCKEmkaZ",
        "symbol": "XLM",
        "name": "Stellar",
        "color": "#000000",
        "iconUrl": "https://cdn.coinranking.com/78CxK1xsp/Stellar_symbol_black_RGB.svg",
        "marketCap": "2069089898",
        "price": "0.10240219172840055",
        "listedAt": 1484611200,
        "tier": 1,
        "change": "-0.89",
        "rank": 33,
        "sparkline": [
          "0.10325224812190384",
          "0.10366916578981278",
          "0.10363288382418535",
          "0.1049864511925249",
          "0.10498011570879018",
          "0.1046058218768745",
          "0.10434690183341849",
          "0.10345817865351259",
          "0.10384150886597171",
          "0.10354604736943414",
          "0.10354882844069035",
          "0.1024384640954094",
          "0.10234619386910233",
          "0.10248189339707947",
          "0.10258655219551421",
          "0.10244671058600922",
          "0.10240440329835981",
          "0.10273309480771908",
          "0.10281691631645054",
          "0.10261609153066056",
          "0.10221340044777313",
          "0.10217508374380667",
          "0.10236514303861458",
          "0.1019849335746699",
          "0.1020323103927201"
        ],
        "lowVolume": false,
        "coinrankingUrl": "https://coinranking.com/coin/f3iaFeCKEmkaZ+stellar-xlm",
        "24hVolume": "174694581",
        "btcPrice": "0.000005190442644811"
      },
      {
        "uuid": "TpHE2IShQw-sJ",
        "symbol": "ALGO",
        "name": "Algorand",
        "color": null,
        "iconUrl": "https://cdn.coinranking.com/lzbmCkUGB/algo.svg",
        "marketCap": "2044822274",
        "price": "0.2954936608872931",
        "listedAt": 1562082540,
        "tier": 1,
        "change": "0.33",
        "rank": 34,
        "sparkline": [
          "0.2942680827561112",
          "0.29425494710950634",
          "0.2945299660890899",
          "0.29881265159853304",
          "0.2990791745138703",
          "0.29740466327837245",
          "0.29766971112456503",
          "0.2959150976065735",
          "0.2969979400383497",
          "0.2967340991664984",
          "0.2973012421682273",
          "0.2927118355845283",
          "0.29265100445312564",
          "0.2948519054113202",
          "0.29532313403116917",
          "0.29558585241000335",
          "0.29535648988078006",
          "0.2966451212731599",
          "0.2960977345424843",
          "0.29444849860715544",
          "0.29386732365864204",
          "0.2949973022680915",
          "0.29643948881146026",
          "0.2950783519233359",
          "0.2946407566915097"
        ],
        "lowVolume": false,
        "coinrankingUrl": "https://coinranking.com/coin/TpHE2IShQw-sJ+algorand-algo",
        "24hVolume": "69816847",
        "btcPrice": "0.00001497763742019"
      },
      {
        "uuid": "AaQUAs2Mc",
        "symbol": "LUNC",
        "name": "Terra Classic",
        "color": "#0E3CA5",
        "iconUrl": "https://cdn.coinranking.com/F-PJdF8Um/LUNA.svg",
        "marketCap": "1914910391",
        "price": "0.000290499910593247",
        "listedAt": 1565957940,
        "tier": 1,
        "change": "8.98",
        "rank": 35,
        "sparkline": [
          "0.000263826241071447",
          "0.000268468745435094",
          "0.00027749457861736",
          "0.000278842063812384",
          "0.00028103448427949",
          "0.000278848697063495",
          "0.0002778789482848",
          "0.000277202626030695",
          "0.000277607455591066",
          "0.000274219945413354",
          "0.000273924199955477",
          "0.0002618483816701",
          "0.00025760642767324",
          "0.000257658307449915",
          "0.000253398188959539",
          "0.000247145617782315",
          "0.000247962812182383",
          "0.000248791899800076",
          "0.000253108126979081",
          "0.000252946258758531",
          "0.00026018546159319",
          "0.000267303014685262",
          "0.000287606614170945",
          "0.000291483837065571",
          "0.000294135541492536"
        ],
        "lowVolume": false,
        "coinrankingUrl": "https://coinranking.com/coin/AaQUAs2Mc+terraclassic-lunc",
        "24hVolume": "388697065",
        "btcPrice": "1.472452004e-8"
      },
      {
        "uuid": "08CsQa-Ov",
        "symbol": "WEMIX",
        "name": "WEMIX TOKEN",
        "color": "#9bdc70",
        "iconUrl": "https://cdn.coinranking.com/1N84MQsoO/7548.png",
        "marketCap": "1882601242",
        "price": "1.882601242036994",
        "listedAt": 1638249982,
        "tier": 1,
        "change": "-1.98",
        "rank": 36,
        "sparkline": [
          "1.914410661053378",
          "1.9185412659595518",
          "1.9246348634211439",
          "1.9296759354665955",
          "1.9415078736049047",
          "1.9339435997721874",
          "1.9347761288321121",
          "1.9303479296040398",
          "1.9298798767955072",
          "1.9262067114819483",
          "1.9274405171284508",
          "1.9128569113923497",
          "1.908977427567073",
          "1.9145339517461806",
          "1.9209914478642305",
          "1.9208178018122561",
          "1.913535501808357",
          "1.9132584665882797",
          "1.9092863093398953",
          "1.9105017130051156",
          "1.8923144734246333",
          "1.8919376076063075",
          "1.8965041836257788",
          "1.8977650512005952",
          "1.8865338263797002"
        ],
        "lowVolume": false,
        "coinrankingUrl": "https://coinranking.com/coin/08CsQa-Ov+wemixtoken-wemix",
        "24hVolume": "10836710",
        "btcPrice": "0.000095423092073652"
      },
      {
        "uuid": "lORNHeWV9",
        "symbol": "MIM",
        "name": "Magic Internet Money",
        "color": "#8838ff",
        "iconUrl": "https://cdn.coinranking.com/oLYNt8laX/mimlogopng.png",
        "marketCap": "1810220110",
        "price": "0.9967525195672633",
        "listedAt": 1627436833,
        "tier": 1,
        "change": "-0.31",
        "rank": 37,
        "sparkline": [
          "0.9987549626766409",
          "0.9986946183512333",
          "0.9994702124771849",
          "0.9972358072363142",
          "1.0005641366632523",
          "0.9988617784091964",
          "0.9981189560712164",
          "0.9984827145690263",
          "0.9987885399088777",
          "0.9996497965249108",
          "0.9991828071344336",
          "1.0027636740162935",
          "0.9975086977807687",
          "0.9980244049932231",
          "0.9986572680147698",
          "0.9972384428986717",
          "0.9977570827083927",
          "0.9988583871251063",
          "0.9991726712031151",
          "0.9982075225489555",
          "0.997824128032999",
          "0.9986837676397317",
          "0.9993599954238451",
          "0.9987328466481253",
          "0.9969586125411233"
        ],
        "lowVolume": false,
        "coinrankingUrl": "https://coinranking.com/coin/lORNHeWV9+magicinternetmoney-mim",
        "24hVolume": "101294",
        "btcPrice": "0.000050522227078953"
      },
      {
        "uuid": "9_jH48RBW",
        "symbol": "BTCB",
        "name": "Bitcoin BEP2",
        "color": "#ff9d14",
        "iconUrl": "https://cdn.coinranking.com/Swr_SeZio/4023.png",
        "marketCap": "1686557743",
        "price": "19727.131311829406",
        "listedAt": 1629334963,
        "tier": 1,
        "change": "-1.75",
        "rank": 38,
        "sparkline": [
          "20056.082384675123",
          "20040.984534654493",
          "20119.663434889022",
          "20159.601398404513",
          "20187.716789890124",
          "20121.023193031808",
          "20126.227320838483",
          "20128.398781879558",
          "20161.256819564598",
          "20128.12503738571",
          "20083.20827790784",
          "19843.73205230674",
          "19750.53367486402",
          "19830.606670471843",
          "19857.216939119586",
          "19804.023075008357",
          "19758.548773573046",
          "19815.89993159418",
          "19826.8992784704",
          "19787.270406139894",
          "19710.73033667643",
          "19710.02219851159",
          "19752.037997478972",
          "19742.56668604438",
          "19717.465255598967"
        ],
        "lowVolume": false,
        "coinrankingUrl": "https://coinranking.com/coin/9_jH48RBW+bitcoinbep2-btcb",
        "24hVolume": "5796778",
        "btcPrice": "0.999905782214888"
      },
      {
        "uuid": "Z96jIvLU7",
        "symbol": "IMX",
        "name": "Immutable X",
        "color": "#000000",
        "iconUrl": "https://cdn.coinranking.com/naRGT2Y_X/10603.png",
        "marketCap": "1610689282",
        "price": "0.8053446408374678",
        "listedAt": 1649387294,
        "tier": 1,
        "change": "1.45",
        "rank": 39,
        "sparkline": [
          "0.7907327404971215",
          "0.7923899752132737",
          "0.7968797757884885",
          "0.8138189798358935",
          "0.81417203314429",
          "0.809381779158838",
          "0.8085919323406732",
          "0.8040727542210309",
          "0.8079635592505987",
          "0.8091392313771687",
          "0.806310495650946",
          "0.7901320277492275",
          "0.7886270738603625",
          "0.7944140009973711",
          "0.7983475748373753",
          "0.8009357254425932",
          "0.802614341592139",
          "0.8039774259317556",
          "0.8033847473425608",
          "0.7986726565935633",
          "0.7961369847060086",
          "0.7955289067589015",
          "0.8003141356559206",
          "0.8008197223294987",
          "0.8032643973684649"
        ],
        "lowVolume": false,
        "coinrankingUrl": "https://coinranking.com/coin/Z96jIvLU7+immutablex-imx",
        "24hVolume": "31173945",
        "btcPrice": "0.000040820368168091"
      },
      {
        "uuid": "ncYFcP709",
        "symbol": "CAKE",
        "name": "PancakeSwap",
        "color": "#fe9555",
        "iconUrl": "https://cdn.coinranking.com/aRtgdw7bQ/pancakeswap-cake-logo.png",
        "marketCap": "1603110748",
        "price": "4.106798691163029",
        "listedAt": 1613642379,
        "tier": 1,
        "change": "0.07",
        "rank": 40,
        "sparkline": [
          "4.100785809690985",
          "4.096915847483178",
          "4.092686392486925",
          "4.129666567922132",
          "4.135239628940718",
          "4.1047211846567375",
          "4.086585963393079",
          "4.063921626539081",
          "4.079667401314245",
          "4.140151172900214",
          "4.135918123021789",
          "4.075526311068936",
          "4.0617946862775165",
          "4.071338232092451",
          "4.079049391619611",
          "4.078066720240643",
          "4.061959406815482",
          "4.068717380913853",
          "4.073983583905934",
          "4.06242321894138",
          "4.054977477944536",
          "4.070826185787463",
          "4.122653156199485",
          "4.117958927112169",
          "4.094951495736463"
        ],
        "lowVolume": false,
        "coinrankingUrl": "https://coinranking.com/coin/ncYFcP709+pancakeswap-cake",
        "24hVolume": "51694069",
        "btcPrice": "0.000208160613561893"
      },
      {
        "uuid": "tEf7-dnwV3BXS",
        "symbol": "MANA",
        "name": "Decentraland",
        "color": "#f47e33",
        "iconUrl": "https://cdn.coinranking.com/ph_svUzXs/decentraland(1).svg",
        "marketCap": "1579461242",
        "price": "0.72005181009529",
        "listedAt": 1500336000,
        "tier": 1,
        "change": "-0.35",
        "rank": 41,
        "sparkline": [
          "0.7229343376607444",
          "0.7244643756042997",
          "0.7257145540121258",
          "0.7358633801733236",
          "0.7371911416090371",
          "0.7340944836367508",
          "0.7345521105244802",
          "0.729881415559142",
          "0.7335659642227856",
          "0.7329985236018723",
          "0.7314370260610538",
          "0.7203459131011694",
          "0.7186961314100574",
          "0.7231807295018211",
          "0.7246041345291167",
          "0.7244664194222551",
          "0.7238799541610814",
          "0.7263215046120699",
          "0.7258997676826848",
          "0.7218418240214732",
          "0.7195679672720593",
          "0.7173806849291221",
          "0.7200949861880611",
          "0.7176731631260037",
          "0.7179596237572625"
        ],
        "lowVolume": false,
        "coinrankingUrl": "https://coinranking.com/coin/tEf7-dnwV3BXS+decentraland-mana",
        "24hVolume": "205654694",
        "btcPrice": "0.000036497144821905"
      },
      {
        "uuid": "aMNLwaUbY",
        "symbol": "ICP",
        "name": "Internet Computer (DFINITY)",
        "color": "#00042b",
        "iconUrl": "https://cdn.coinranking.com/1uJ_RVrmC/dfinity-icp.png",
        "marketCap": "1574057230",
        "price": "6.047534248580015",
        "listedAt": 1601555742,
        "tier": 1,
        "change": "-1.98",
        "rank": 42,
        "sparkline": [
          "6.13060407380442",
          "6.168090037652414",
          "6.164771896818114",
          "6.269283759228216",
          "6.261277252882088",
          "6.2271806949518975",
          "6.214580305178403",
          "6.176308022120759",
          "6.182850713012731",
          "6.226468962677012",
          "6.229129323658351",
          "6.0773175710933245",
          "6.131618646184886",
          "6.18729234818",
          "6.16449408528137",
          "6.154984607766304",
          "6.161968475253702",
          "6.187594943484165",
          "6.144752423162828",
          "6.092147904297903",
          "6.1260578944968325",
          "6.070712461086283",
          "6.0386537230588235",
          "6.000154373564449",
          "6.028741534377859"
        ],
        "lowVolume": false,
        "coinrankingUrl": "https://coinranking.com/coin/aMNLwaUbY+internetcomputerdfinity-icp",
        "24hVolume": "192548475",
        "btcPrice": "0.000306530349887804"
      },
      {
        "uuid": "FEbS54wxo4oIl",
        "symbol": "VET",
        "name": "VeChain",
        "color": "#4bc0fa",
        "iconUrl": "https://cdn.coinranking.com/B1_TDu9Dm/VEN.svg",
        "marketCap": "1552176508",
        "price": "0.0232498393133407",
        "listedAt": 1533427200,
        "tier": 1,
        "change": "-0.89",
        "rank": 43,
        "sparkline": [
          "0.023501313042796172",
          "0.023614310401137317",
          "0.023646762083176467",
          "0.023896016889499397",
          "0.023856708393620377",
          "0.023695827651913297",
          "0.023692022587406696",
          "0.023571392879647882",
          "0.023684917304224975",
          "0.023642303273641533",
          "0.023588568374606367",
          "0.023265995051424515",
          "0.023235218753521768",
          "0.023357198760266276",
          "0.023378917047134004",
          "0.023362024815116508",
          "0.023379591335856702",
          "0.023433425492063203",
          "0.02341333559880395",
          "0.023280782148786833",
          "0.02316342248524219",
          "0.02317878631347388",
          "0.023296962853047432",
          "0.023215674977686163",
          "0.023177203637325415"
        ],
        "lowVolume": false,
        "coinrankingUrl": "https://coinranking.com/coin/FEbS54wxo4oIl+vechain-vet",
        "24hVolume": "94898009",
        "btcPrice": "0.000001178460689367"
      },
      {
        "uuid": "SbWqqTui-",
        "symbol": "ENS",
        "name": "EnergySwap",
        "color": "#ffda55",
        "iconUrl": "https://cdn.coinranking.com/fmYxEUV5a/cropped-logo37-Converted-01-192x192.png",
        "marketCap": "1453042945",
        "price": "14.53042944692884",
        "listedAt": 1626134763,
        "tier": 1,
        "change": "3.10",
        "rank": 44,
        "sparkline": [
          "14.045298033844489",
          "14.021729834754192",
          "14.021629565664972",
          "14.380516555700305",
          "14.54520324315631",
          "14.372373044862007",
          "14.45397842416768",
          "14.320368738052878",
          "14.511393410275783",
          "14.484168173686232",
          "14.52821086418655",
          "14.163015970043649",
          "14.190165875905958",
          "14.264868376298972",
          "14.339424161146265",
          "14.379977324402898",
          "14.39375245252799",
          "14.445924718118942",
          "14.429193511146568",
          "14.278311961665347",
          "14.218738171493532",
          "14.130764643469226",
          "14.250043719700727",
          "14.338118497161291",
          "14.493331344260234"
        ],
        "lowVolume": false,
        "coinrankingUrl": "https://coinranking.com/coin/SbWqqTui-+energyswap-ens",
        "24hVolume": "15930833",
        "btcPrice": "0.000736205207365584"
      },
      {
        "uuid": "KfWtaeV1W",
        "symbol": "FRAX",
        "name": "Frax",
        "color": "#000000",
        "iconUrl": "https://cdn.coinranking.com/BpVNCX-NM/frax.png",
        "marketCap": "1420927493",
        "price": "0.9987200502291066",
        "listedAt": 1615299931,
        "tier": 1,
        "change": "-0.24",
        "rank": 45,
        "sparkline": [
          "1.0006014037745485",
          "1.0001660433194146",
          "1.0006878865709765",
          "0.9978203595555055",
          "1.0001898003042327",
          "1.0001076816718806",
          "0.999135205667488",
          "0.9994079199716889",
          "0.9989571751856859",
          "0.9995964282125978",
          "0.9993596474243271",
          "1.005146490415938",
          "0.9988198992185551",
          "0.99748495887305",
          "0.9993534957414536",
          "0.999287342478478",
          "0.998511091355287",
          "0.9989528485490347",
          "0.9990187836448269",
          "1.0002800276907262",
          "0.9993592035430255",
          "0.9998579653911273",
          "0.9985904373801939",
          "0.9995641544164022",
          "0.9992621808259705"
        ],
        "lowVolume": false,
        "coinrankingUrl": "https://coinranking.com/coin/KfWtaeV1W+frax-frax",
        "24hVolume": "2612001",
        "btcPrice": "0.000050621954974224"
      },
      {
        "uuid": "iAzbfXiBBKkR6",
        "symbol": "EOS",
        "name": "EOS",
        "color": "#443f54",
        "iconUrl": "https://cdn.coinranking.com/PqOYrWSje/eos2.svg",
        "marketCap": "1397491133",
        "price": "1.4141888172468031",
        "listedAt": 1498694400,
        "tier": 1,
        "change": "-0.45",
        "rank": 46,
        "sparkline": [
          "1.4199365886435844",
          "1.431807510022964",
          "1.4371211911512474",
          "1.4573199019121132",
          "1.462434661178904",
          "1.4556681952847945",
          "1.4589769949568512",
          "1.4530514306642983",
          "1.4549807887957853",
          "1.4540946229177907",
          "1.4538825182985966",
          "1.418405345150752",
          "1.407331622088607",
          "1.418808897607807",
          "1.4231681699833911",
          "1.4207713427607063",
          "1.4183563407730735",
          "1.4215463658103724",
          "1.4212837476180884",
          "1.4002377855105972",
          "1.3840561786591747",
          "1.4093410857851807",
          "1.43236934415852",
          "1.4152545169451765",
          "1.4107716017700376"
        ],
        "lowVolume": false,
        "coinrankingUrl": "https://coinranking.com/coin/iAzbfXiBBKkR6+eos-eos",
        "24hVolume": "453067538",
        "btcPrice": "0.00007168075039176"
      },
      {
        "uuid": "fsIbGOEJWbzxG",
        "symbol": "XTZ",
        "name": "Tezos",
        "color": "#2c7df7",
        "iconUrl": "https://cdn.coinranking.com/HkLUdilQ7/xtz.svg",
        "marketCap": "1381226427",
        "price": "1.5208620536024553",
        "listedAt": 1530662400,
        "tier": 1,
        "change": "-1.14",
        "rank": 47,
        "sparkline": [
          "1.5375415524198517",
          "1.5399184814161948",
          "1.544424998209532",
          "1.569979918277824",
          "1.5682790493252219",
          "1.5610541276318817",
          "1.558275436256777",
          "1.547237318922422",
          "1.5508203934319866",
          "1.5495900180556066",
          "1.552190455139495",
          "1.5310970488711677",
          "1.5394086204688615",
          "1.5513499262019455",
          "1.5492925515702924",
          "1.5464302495556195",
          "1.5418755393742543",
          "1.545188855634624",
          "1.5453820851748772",
          "1.5326566141097329",
          "1.5244668172585694",
          "1.5203814058095246",
          "1.5283435403986962",
          "1.5213890703978192",
          "1.5164313508971863"
        ],
        "lowVolume": false,
        "coinrankingUrl": "https://coinranking.com/coin/fsIbGOEJWbzxG+tezos-xtz",
        "24hVolume": "53517799",
        "btcPrice": "0.000077087678756232"
      },
      {
        "uuid": "Pe93bIOD2",
        "symbol": "LDO",
        "name": "Lido DAO Token",
        "color": "#77cced",
        "iconUrl": "https://cdn.coinranking.com/Wp6LFY6ZZ/8000.png",
        "marketCap": "1379565927",
        "price": "1.7151904517938725",
        "listedAt": 1627361901,
        "tier": 1,
        "change": "1.44",
        "rank": 48,
        "sparkline": [
          "1.693285808448798",
          "1.7165757225945724",
          "1.7584560459372016",
          "1.9001858648502243",
          "2.012374889663841",
          "1.9086498470046347",
          "1.8863054920360225",
          "1.8637811364032777",
          "1.866485975560204",
          "1.8938421649309252",
          "1.86966741280737",
          "1.746229227865371",
          "1.7507537430772515",
          "1.783666832457341",
          "1.792822521698426",
          "1.762570559156012",
          "1.7503457852648867",
          "1.7630604149287434",
          "1.7511385139790119",
          "1.7270414381579267",
          "1.700275396266597",
          "1.6984055150432678",
          "1.7123067421526101",
          "1.7105940099572403",
          "1.7075387945368183"
        ],
        "lowVolume": false,
        "coinrankingUrl": "https://coinranking.com/coin/Pe93bIOD2+lidodaotoken-ldo",
        "24hVolume": "139889547",
        "btcPrice": "0.000086937569545149"
      },
      {
        "uuid": "pxtKbG5rg",
        "symbol": "SAND",
        "name": "The Sandbox",
        "color": "#00adef",
        "iconUrl": "https://cdn.coinranking.com/kd_vwOcnI/sandbox.png",
        "marketCap": "1279955194",
        "price": "0.8536050083288537",
        "listedAt": 1613583024,
        "tier": 1,
        "change": "-2.15",
        "rank": 49,
        "sparkline": [
          "0.871520116975108",
          "0.8728250015245671",
          "0.8738657554579953",
          "0.8852156069773779",
          "0.8860454612003457",
          "0.8821425920995422",
          "0.881656892271718",
          "0.8771853375026911",
          "0.883021083289431",
          "0.8826522416337645",
          "0.8781678142425546",
          "0.8635402918192158",
          "0.8620585957597994",
          "0.8676705572674158",
          "0.8676399217647689",
          "0.867755778444875",
          "0.8670666083725296",
          "0.8686652052294421",
          "0.8664590712285908",
          "0.861003023755097",
          "0.8561804973001006",
          "0.8538791318950288",
          "0.8583512197959258",
          "0.8564640993126351",
          "0.8533411212196873"
        ],
        "lowVolume": false,
        "coinrankingUrl": "https://coinranking.com/coin/pxtKbG5rg+thesandbox-sand",
        "24hVolume": "139796017",
        "btcPrice": "0.000043266533286763"
      },
      {
        "uuid": "rk5XwL6mIjUDp",
        "symbol": "CEL",
        "name": "Celsius Network",
        "color": "#f37425",
        "iconUrl": "https://cdn.coinranking.com/XPU7TeCYD/New-CEL.png",
        "marketCap": "1232877232",
        "price": "1.7796768153031912",
        "listedAt": 1531958400,
        "tier": 1,
        "change": "-7.79",
        "rank": 50,
        "sparkline": [
          "1.9576150660455114",
          "2.0483489881565187",
          "2.990621754160826",
          "3.4993130806548978",
          "2.470859094950815",
          "1.9225692142501323",
          "1.8794248078917823",
          "1.9244976177378341",
          "1.9363429678487483",
          "1.9783580222663066",
          "1.9698323016283605",
          "1.911853404966516",
          "1.8770877165202948",
          "1.8574378577611272",
          "1.8687614314603966",
          "1.8268437043635757",
          "1.7488600394883507",
          "1.769270084148445",
          "1.8141019522025748",
          "1.8405410485607767",
          "1.8311478758352926",
          "1.783914560409463",
          "1.8397683313888817",
          "1.804354421410562",
          "1.794115428430015"
        ],
        "lowVolume": false,
        "coinrankingUrl": "https://coinranking.com/coin/rk5XwL6mIjUDp+celsiusnetwork-cel",
        "24hVolume": "337270901",
        "btcPrice": "0.000090206178991081"
      }
    ]
  }
}